MANIFEST.in
README.rst
setup.cfg
setup.py
tgext/__init__.py
tgext.ecommerce.egg-info/PKG-INFO
tgext.ecommerce.egg-info/SOURCES.txt
tgext.ecommerce.egg-info/dependency_links.txt
tgext.ecommerce.egg-info/entry_points.txt
tgext.ecommerce.egg-info/not-zip-safe
tgext.ecommerce.egg-info/requires.txt
tgext.ecommerce.egg-info/top_level.txt
tgext/ecommerce/__init__.py
tgext/ecommerce/bootstrap.py
tgext/ecommerce/helpers.py
tgext/ecommerce/partials.py
tgext/ecommerce/controllers/__init__.py
tgext/ecommerce/controllers/manage.py
tgext/ecommerce/controllers/root.py
tgext/ecommerce/controllers/sagePayment.py
tgext/ecommerce/lib/__init__.py
tgext/ecommerce/lib/async_jobs.py
tgext/ecommerce/lib/cart.py
tgext/ecommerce/lib/category.py
tgext/ecommerce/lib/exceptions.py
tgext/ecommerce/lib/forms.py
tgext/ecommerce/lib/helpers.py
tgext/ecommerce/lib/order.py
tgext/ecommerce/lib/product.py
tgext/ecommerce/lib/shop.py
tgext/ecommerce/lib/utils.py
tgext/ecommerce/lib/validators.py
tgext/ecommerce/lib/payments/__init__.py
tgext/ecommerce/lib/payments/null_payment.py
tgext/ecommerce/lib/payments/paypal.py
tgext/ecommerce/lib/payments/sage.py
tgext/ecommerce/model/__init__.py
tgext/ecommerce/model/models.py
tgext/ecommerce/public/__init__.py
tgext/ecommerce/public/css/style.css
tgext/ecommerce/public/images/star.png
tgext/ecommerce/templates/__init__.py
tgext/ecommerce/templates/edit_order.html
tgext/ecommerce/templates/message.html
tgext/ecommerce/templates/notes.html
tgext/ecommerce/templates/order_detail.html
tgext/ecommerce/templates/orders.html
tgext/ecommerce/templates/sage_pay.html
tgext/ecommerce/templates/sage_payment_card.html
tgext/ecommerce/tests/__init__.py
tgext/ecommerce/tests/test_product.py