Metadata-Version: 1.0
Name: tgext.ecommerce
Version: 0.1.6
Summary: UNKNOWN
Home-page: UNKNOWN
Author: UNKNOWN
Author-email: UNKNOWN
License: UNKNOWN
Keywords: turbogears2.application
Platform: UNKNOWN
